pfbackup/__init__.py
pfbackup/__main__.py
pfbackup/main.py
pfbackup/pfsense.py
pfbackup-1.1.1.dist-info/LICENSE
pfbackup-1.1.1.dist-info/METADATA
pfbackup-1.1.1.dist-info/WHEEL
pfbackup-1.1.1.dist-info/entry_points.txt
pfbackup-1.1.1.dist-info/top_level.txt
pfbackup-1.1.1.dist-info/RECORD
