Metadata-Version: 2.1
Name: pfbackup
Version: 1.1.1
Summary: pfSense config backup tool
Home-page: https://github.com/mharjac/pfbackup
Author: Mario Harjac
Author-email: m@harja.ch
License: UNKNOWN
Platform: UNKNOWN
Classifier: Programming Language :: Python :: 3
Classifier: License :: OSI Approved :: MIT License
Classifier: Operating System :: OS Independent
Requires-Python: >=3.6
Requires-Dist: requests
